polugins/__init__.py
polugins/_testing/namespaces.py
polugins/_testing/self_register.py
polugins/_types.py
polugins/_version.py
polugins/main.py
polugins/pl.py
polugins-0.5.2.dist-info/WHEEL
polugins-0.5.2.dist-info/entry_points.txt
polugins-0.5.2.dist-info/METADATA
polugins-0.5.2.dist-info/RECORD
