Metadata-Version: 2.3
Name: polugins
Version: 0.5.2
Summary: Plugin system for Polars.
Author: StefanBRas
Author-email: StefanBRas <opensource@bruhn.io>
Requires-Dist: polars>0.16.13
Requires-Dist: typing-extensions>=4.4.0
Requires-Dist: tomli>=0.2.0
Requires-Python: >=3.8
